samplespace/__init__.py
samplespace/algorithms.py
samplespace/distributions.py
samplespace/pyyaml_support.py
samplespace/repeatablerandom.py
pysamplespace-1.0.4.dist-info/LICENSE
pysamplespace-1.0.4.dist-info/WHEEL
pysamplespace-1.0.4.dist-info/METADATA
pysamplespace-1.0.4.dist-info/RECORD
