Metadata-Version: 2.1
Name: pysamplespace
Version: 1.0.4
Summary: SampleSpace is a cross-platform library for describing and sampling from random distributions.
Home-page: https://gitlab.com/cvpines/pysamplespace
License: BSD-3-Clause
Keywords: random,distribution,sampling,simulation,pcg
Author: Coriander V. Pines
Author-email: contact@corianderpines.org
Requires-Python: >=3.7,<4.0
Classifier: Development Status :: 5 - Production/Stable
Classifier: Intended Audience :: Developers
Classifier: License :: OSI Approved :: BSD License
Classifier: Programming Language :: Python :: 3
Classifier: Programming Language :: Python :: 3.7
Classifier: Programming Language :: Python :: 3.8
Classifier: Programming Language :: Python :: 3.9
Classifier: Topic :: Artistic Software
Classifier: Topic :: Games/Entertainment
Classifier: Topic :: Scientific/Engineering
Classifier: Topic :: Software Development :: Libraries
Classifier: Topic :: Software Development :: Quality Assurance
Classifier: Topic :: Software Development :: Testing
Requires-Dist: xxhash (>=1.4,<2.0)
Project-URL: Documentation, https://pysamplespace.readthedocs.io/en/latest/
Project-URL: Repository, https://gitlab.com/cvpines/pysamplespace
